{
	"info": {
		"_postman_id": "a1b2c3d4-e5f6-7890-abcd-1234567890ab",
		"name": "PurchaseBridge",
		"description": "Colección para pruebas de integración con Helisa y DIAN XML.",
		"schema": "https://schema.getpostman.com/json/collection/v2.1.0/collection.json"
	},
	"item": [
		{
			"name": "Auth",
			"item": [
				{
					"name": "Login Helisa",
					"request": {
						"method": "POST",
						"header": [
							{
								"key": "Content-Type",
								"value": "application/json",
								"type": "text"
							}
						],
						"body": {
							"mode": "raw",
							"raw": "{\n  \"usuario\": \"ADMIN\",\n  \"clave\": \"1234\"\n}"
						},
						"url": {
							"raw": "http://localhost:9000/auth/login",
							"protocol": "http",
							"host": [
								"localhost"
							],
							"port": "9000",
							"path": [
								"auth",
								"login"
							]
						}
					},
					"response": [
						{
							"name": "Éxito",
							"status": "OK",
							"code": 200,
							"_postman_previewlanguage": "json",
							"body": "{\n  \"success\": true,\n  \"usuario\": {\n    \"codigo\": 1,\n    \"nombre\": \"ADMIN\"\n  },\n  \"empresa\": {\n    \"codigo\": 0,\n    \"nombre\": \"EMPRESA DEMO\",\n    \"identidad\": \"900123456\",\n    \"anoActual\": 2026\n  },\n  \"token\": \"eyJhbGciOiJIUzI1...\"\n}"
						}
					]
				}
			]
		},
		{
			"name": "XML (Original)",
			"item": [
				{
					"name": "Listar Archivos (FS)",
					"request": {
						"method": "GET",
						"header": [],
						"url": {
							"raw": "http://localhost:9000/xml/list",
							"protocol": "http",
							"host": [
								"localhost"
							],
							"port": "9000",
							"path": [
								"xml",
								"list"
							]
						}
					},
					"response": [
						{
							"name": "Éxito",
							"status": "OK",
							"code": 200,
							"_postman_previewlanguage": "json",
							"body": "[\n    {\n        \"fileName\": \"factura1.xml\",\n        \"size\": 24567,\n        \"lastModified\": \"2026-03-17 14:30:00\"\n    }\n]"
						}
					]
				},
				{
					"name": "Subir Archivo XML",
					"request": {
						"method": "POST",
						"header": [],
						"body": {
							"mode": "formdata",
							"formdata": [
								{
									"key": "file",
									"type": "file",
									"src": []
								}
							]
						},
						"url": {
							"raw": "http://localhost:9000/xml/upload",
							"protocol": "http",
							"host": [
								"localhost"
							],
							"port": "9000",
							"path": [
								"xml",
								"upload"
							]
						}
					},
					"response": [
						{
							"name": "Éxito",
							"status": "OK",
							"code": 200,
							"_postman_previewlanguage": "json",
							"body": "{\n    \"success\": true,\n    \"message\": \"XML uploaded successfully\",\n    \"fileName\": \"factura.xml\",\n    \"path\": \"PurchaseBridge/Input/factura.xml\"\n}"
						}
					]
				},
				{
					"name": "Parsear Archivo XML",
					"request": {
						"method": "POST",
						"header": [
							{
								"key": "Content-Type",
								"value": "application/json",
								"type": "text"
							}
						],
						"body": {
							"mode": "raw",
							"raw": "{\n  \"fileName\": \"factura1.xml\"\n}"
						},
						"url": {
							"raw": "http://localhost:9000/xml/parse",
							"protocol": "http",
							"host": [
								"localhost"
							],
							"port": "9000",
							"path": [
								"xml",
								"parse"
							]
						}
					},
					"response": [
						{
							"name": "Éxito",
							"status": "OK",
							"code": 200,
							"_postman_previewlanguage": "json",
							"body": "{\n    \"success\": true,\n    \"proveedor\": { ... },\n    \"productos\": [ ... ],\n    \"totales\": { ... }\n}"
						}
					]
				}
			]
		},
		{
			"name": "XML Staging (Nuevo)",
			"item": [
				{
					"name": "Listar Archivos (Bandeja)",
					"request": {
						"method": "GET",
						"header": [
							{
								"key": "Authorization",
								"value": "Bearer {{token}}",
								"type": "text"
							}
						],
						"url": {
							"raw": "http://localhost:9000/xml/files",
							"protocol": "http",
							"host": [
								"localhost"
							],
							"port": "9000",
							"path": [
								"xml",
								"files"
							]
						}
					},
					"response": [
						{
							"name": "Éxito",
							"status": "OK",
							"code": 200,
							"_postman_previewlanguage": "json",
							"body": "[\n    {\n        \"id\": 1,\n        \"file_name\": \"factura1.xml\",\n        \"proveedor_nombre\": \"CERAMICA SAS\",\n        \"fecha_documento\": \"2026-03-14 00:00:00\",\n        \"estado\": \"VALIDADO\",\n        \"fecha_carga\": \"2026-03-17 18:00:00\"\n    }\n]"
						}
					]
				},
				{
					"name": "Detalle de Archivo",
					"request": {
						"method": "GET",
						"header": [
							{
								"key": "Authorization",
								"value": "Bearer {{token}}",
								"type": "text"
							}
						],
						"url": {
							"raw": "http://localhost:9000/xml/files/1",
							"protocol": "http",
							"host": [
								"localhost"
							],
							"port": "9000",
							"path": [
								"xml",
								"files",
								"1"
							]
						}
					},
					"response": []
				},
				{
					"name": "Validar y Persistir XML",
					"request": {
						"method": "POST",
						"header": [
							{
								"key": "Content-Type",
								"value": "application/json",
								"type": "text"
							},
							{
								"key": "Authorization",
								"value": "Bearer {{token}}",
								"type": "text"
							}
						],
						"body": {
							"mode": "raw",
							"raw": "{\n  \"fileName\": \"factura1.xml\"\n}"
						},
						"url": {
							"raw": "http://localhost:9000/xml/validate",
							"protocol": "http",
							"host": [
								"localhost"
							],
							"port": "9000",
							"path": [
								"xml",
								"validate"
							]
						}
					},
					"response": []
				},
				{
					"name": "Productos Pendientes",
					"request": {
						"method": "GET",
						"header": [
							{
								"key": "Authorization",
								"value": "Bearer {{token}}",
								"type": "text"
							}
						],
						"url": {
							"raw": "http://localhost:9000/xml/productos/pendientes",
							"protocol": "http",
							"host": [
								"localhost"
							],
							"port": "9000",
							"path": [
								"xml",
								"productos",
								"pendientes"
							]
						}
					},
					"response": []
				},
				{
					"name": "Procesar XML",
					"request": {
						"method": "POST",
						"header": [
							{
								"key": "Content-Type",
								"value": "application/json",
								"type": "text"
							},
							{
								"key": "Authorization",
								"value": "Bearer {{token}}",
								"type": "text"
							}
						],
						"body": {
							"mode": "raw",
							"raw": "{\n  \"ids\": [1]\n}"
						},
						"url": {
							"raw": "http://localhost:9000/xml/procesar",
							"protocol": "http",
							"host": [
								"localhost"
							],
							"port": "9000",
							"path": [
								"xml",
								"procesar"
							]
						}
					},
					"response": []
				}
			]
		},
		{
			"name": "Equivalencias",
			"item": [
				{
					"name": "Listar Equivalencias",
					"request": {
						"method": "GET",
						"header": [],
						"url": {
							"raw": "http://localhost:9000/equivalencias?limite=50",
							"protocol": "http",
							"host": [
								"localhost"
							],
							"port": "9000",
							"path": [
								"equivalencias"
							],
							"query": [
								{
									"key": "limite",
									"value": "50"
								}
							]
						}
					},
					"response": []
				},
				{
					"name": "Crear Equivalencia",
					"request": {
						"method": "POST",
						"header": [
							{
								"key": "Content-Type",
								"value": "application/json",
								"type": "text"
							}
						],
						"body": {
							"mode": "raw",
							"raw": "{\n  \"codigoH\": 123,\n  \"referenciaH\": \"REF-H\",\n  \"referenciaP\": \"REF-P\",\n  \"unidadP\": \"94\",\n  \"factor\": 1\n}"
						},
						"url": {
							"raw": "http://localhost:9000/equivalencias",
							"protocol": "http",
							"host": [
								"localhost"
							],
							"port": "9000",
							"path": [
								"equivalencias"
							]
						}
					},
					"response": []
				}
			]
		},
		{
			"name": "Ping",
			"request": {
				"method": "GET",
				"header": [],
				"url": {
					"raw": "http://localhost:9000/ping",
					"protocol": "http",
					"host": [
						"localhost"
					],
					"port": "9000",
					"path": [
						"ping"
					]
				}
			},
			"response": []
		}
	]
}
