{
	"info": {
		"_postman_id": "a1b2c3d4-e5f6-7890-abcd-1234567890ab",
		"name": "PurchaseBridge",
		"description": "Colección para pruebas de integración con Helisa y DIAN XML.",
		"schema": "https://schema.getpostman.com/json/collection/v2.1.0/collection.json"
	},
	"item": [
		{
			"name": "Ping",
			"request": {
				"method": "GET",
				"header": [],
				"url": {
					"raw": "http://localhost:9000/ping",
					"protocol": "http",
					"host": [
						"localhost"
					],
					"port": "9000",
					"path": [
						"ping"
					]
				}
			},
			"response": []
		},
		{
			"name": "Listar Archivos XML",
			"request": {
				"method": "GET",
				"header": [],
				"url": {
					"raw": "http://localhost:9000/xml/list",
					"protocol": "http",
					"host": [
						"localhost"
					],
					"port": "9000",
					"path": [
						"xml",
						"list"
					]
				}
			},
			"response": []
		},
		{
			"name": "Subir Archivo XML",
			"request": {
				"method": "POST",
				"header": [],
				"body": {
					"mode": "formdata",
					"formdata": [
						{
							"key": "file",
							"type": "file",
							"src": []
						}
					]
				},
				"url": {
					"raw": "http://localhost:9000/xml/upload",
					"protocol": "http",
					"host": [
						"localhost"
					],
					"port": "9000",
					"path": [
						"xml",
						"upload"
					]
				}
			},
			"response": []
		},
		{
			"name": "Validar Proveedor",
			"request": {
				"method": "GET",
				"header": [],
				"url": {
					"raw": "http://localhost:9000/proveedor/860002536?anio=2026",
					"protocol": "http",
					"host": [
						"localhost"
					],
					"port": "9000",
					"path": [
						"proveedor",
						"860002536"
					],
					"query": [
						{
							"key": "anio",
							"value": "2026"
						}
					]
				}
			},
			"response": []
		},
		{
			"name": "Procesar Factura XML",
			"request": {
				"method": "POST",
				"header": [
					{
						"key": "Content-Type",
						"value": "application/xml",
						"type": "text"
					}
				],
				"body": {
					"mode": "raw",
					"raw": "<?xml version=\"1.0\" encoding=\"UTF-8\"?>\n<Invoice xmlns:cac=\"urn:oasis:names:specification:ubl:schema:xsd:CommonAggregateComponents-2\" xmlns:cbc=\"urn:oasis:names:specification:ubl:schema:xsd:CommonBasicComponents-2\" xmlns:ds=\"http://www.w3.org/2000/09/xmldsig#\" xmlns:ext=\"urn:oasis:names:specification:ubl:schema:xsd:CommonExtensionComponents-2\" xmlns:sts=\"dian:gov:co:facturaelectronica:Structures-2-1\" xmlns:xades=\"http://uri.etsi.org/01903/v1.3.2#\" xmlns:xades141=\"http://uri.etsi.org/01903/v1.4.1#\" xmlns:xsi=\"http://www.w3.org/2001/XMLSchema-instance\">\n    <cbc:IssueDate>2026-05-22</cbc:IssueDate>\n    <cac:AccountingSupplierParty>\n        <cac:Party>\n            <cac:PartyTaxScheme>\n                <cbc:CompanyID schemeAgencyID=\"195\" schemeID=\"5\" schemeName=\"31\">860002536</cbc:CompanyID>\n            </cac:PartyTaxScheme>\n        </cac:Party>\n    </cac:AccountingSupplierParty>\n    <cac:InvoiceLine>\n        <cbc:ID>1</cbc:ID>\n        <cac:Item>\n            <cbc:Description>LAVAMANOS ALUVIA 60 CM BNE EN CJ 7704372060916</cbc:Description>\n            <cac:SellersItemIdentification>\n                <cbc:ID>O60691031</cbc:ID>\n            </cac:SellersItemIdentification>\n        </cac:Item>\n    </cac:InvoiceLine>\n</Invoice>"
				},
				"url": {
					"raw": "http://localhost:9000/factura/xml",
					"protocol": "http",
					"host": [
						"localhost"
					],
					"port": "9000",
					"path": [
						"factura",
						"xml"
					]
				}
			},
			"response": []
		},
		{
			"name": "Parsear Archivo XML",
			"request": {
				"method": "POST",
				"header": [
					{
						"key": "Content-Type",
						"value": "application/json",
						"type": "text"
					}
				],
				"body": {
					"mode": "raw",
					"raw": "{\n  \"fileName\": \"ad086000253602726330020260314073312852.xml\"\n}"
				},
				"url": {
					"raw": "http://localhost:9000/xml/parse",
					"protocol": "http",
					"host": [
						"localhost"
					],
					"port": "9000",
					"path": [
						"xml",
						"parse"
					]
				}
			},
			"response": [
				{
					"name": "Respuesta Exitosa",
					"originalRequest": {
						"method": "POST",
						"header": [
							{
								"key": "Content-Type",
								"value": "application/json",
								"type": "text"
							}
						],
						"body": {
							"mode": "raw",
							"raw": "{\n  \"fileName\": \"ad086000253602726330020260314073312852.xml\"\n}"
						},
						"url": {
							"raw": "http://localhost:9000/xml/parse",
							"protocol": "http",
							"host": [
								"localhost"
							],
							"port": "9000",
							"path": [
								"xml",
								"parse"
							]
						}
					},
					"status": "OK",
					"code": 200,
					"_postman_previewlanguage": "json",
					"header": [
						{
							"key": "Content-Type",
							"value": "application/json"
						}
					],
					"cookie": [],
					"body": "{\n  \"success\": true,\n  \"proveedor\": {\n    \"nit\": \"860002536\",\n    \"nombre\": \"COMPAÑIA COLOMBIANA DE CERAMICA S A S\",\n    \"nombreLegal\": \"COMPAÑIA COLOMBIANA DE CERAMICA S A S\",\n    \"tipoIdentificacion\": \"31\",\n    \"direccion\": \"CL 100 8 A 55 TO C P 9\"\n  },\n  \"productos\": [\n    {\n      \"idLinea\": \"1\",\n      \"descripcion\": \"LAVAMANOS ALUVIA 60 CM BNE EN CJ 7704372060916\",\n      \"referencia\": \"O60691031\",\n      \"referenciaEstandar\": \"7704372060916\",\n      \"cantidad\": 5,\n      \"unidad\": \"94\",\n      \"precioBase\": 277247.8,\n      \"valorUnitario\": 277247.8,\n      \"valorTotal\": 1386239,\n      \"impuesto\": 263385.41,\n      \"porcentajeImpuesto\": 19\n    }\n  ],\n  \"totales\": {\n    \"subtotal\": 1386239.0,\n    \"taxExclusiveAmount\": 1386239.0,\n    \"taxInclusiveAmount\": 1649624.41,\n    \"impuestoTotal\": 263385.41,\n    \"total\": 1649624.41\n  }\n}"
				}
			]
		},
		{
			"name": "Validar Archivo XML",
			"request": {
				"method": "POST",
				"header": [
					{
						"key": "Content-Type",
						"value": "application/json",
						"type": "text"
					}
				],
				"body": {
					"mode": "raw",
					"raw": "{\n  \"fileName\": \"ad086000253602726330020260314073312852.xml\"\n}"
				},
				"url": {
					"raw": "http://localhost:9000/xml/validate",
					"protocol": "http",
					"host": [
						"localhost"
					],
					"port": "9000",
					"path": [
						"xml",
						"validate"
					]
				}
			},
			"response": [
				{
					"name": "Respuesta Exitosa",
					"originalRequest": {
						"method": "POST",
						"header": [
							{
								"key": "Content-Type",
								"value": "application/json",
								"type": "text"
							}
						],
						"body": {
							"mode": "raw",
							"raw": "{\n  \"fileName\": \"ad086000253602726330020260314073312852.xml\"\n}"
						},
						"url": {
							"raw": "http://localhost:9000/xml/validate",
							"protocol": "http",
							"host": [
								"localhost"
							],
							"port": "9000",
							"path": [
								"xml",
								"validate"
							]
						}
					},
					"status": "OK",
					"code": 200,
					"_postman_previewlanguage": "json",
					"header": [
						{
							"key": "Content-Type",
							"value": "application/json"
						}
					],
					"cookie": [],
					"body": "{\n    \"valido\": true,\n    \"requiereHomologacion\": false,\n    \"proveedorExiste\": true,\n    \"productos\": [\n        {\n            \"referencia\": \"O60691031\",\n            \"unidad\": \"94\",\n            \"existeEquivalencia\": true\n        }\n    ],\n    \"errores\": []\n}"
				}
			]
		},
		{
			"name": "Crear Equivalencia",
			"request": {
				"method": "POST",
				"header": [
					{
						"key": "Content-Type",
						"value": "application/json",
						"type": "text"
					}
				],
				"body": {
					"mode": "raw",
					"raw": "{\n  \"codigoH\": 123,\n  \"subCodigoH\": 1,\n  \"nombreH\": \"LAVAMANOS ALUVIA\",\n  \"referenciaH\": \"O60691031H\",\n  \"unidadH\": \"MTR\",\n  \"referenciaP\": \"O60691031\",\n  \"unidadP\": \"94\",\n  \"factor\": 1.4\n}"
				},
				"url": {
					"raw": "http://localhost:9000/equivalencia",
					"protocol": "http",
					"host": [
						"localhost"
					],
					"port": "9000",
					"path": [
						"equivalencia"
					]
				}
			},
			"response": [
				{
					"name": "Éxito",
					"originalRequest": {
						"method": "POST",
						"header": [
							{
								"key": "Content-Type",
								"value": "application/json",
								"type": "text"
							}
						],
						"body": {
							"mode": "raw",
							"raw": "{\n  \"codigoH\": 123,\n  \"subCodigoH\": 1,\n  \"nombreH\": \"LAVAMANOS ALUVIA\",\n  \"referenciaH\": \"O60691031H\",\n  \"unidadH\": \"MTR\",\n  \"referenciaP\": \"O60691031\",\n  \"unidadP\": \"94\",\n  \"factor\": 1.4\n}"
						},
						"url": {
							"raw": "http://localhost:9000/equivalencia",
							"protocol": "http",
							"host": [
								"localhost"
							],
							"port": "9000",
							"path": [
								"equivalencia"
							]
						}
					},
					"status": "Created",
					"code": 201,
					"_postman_previewlanguage": "json",
					"header": [
						{
							"key": "Content-Type",
							"value": "application/json"
						}
					],
					"cookie": [],
					"body": "{\n  \"success\": true,\n  \"message\": \"Equivalencia creada correctamente\"\n}"
				},
				{
					"name": "Error duplicado",
					"originalRequest": {
						"method": "POST",
						"header": [
							{
								"key": "Content-Type",
								"value": "application/json",
								"type": "text"
							}
						],
						"body": {
							"mode": "raw",
							"raw": "{\n  \"codigoH\": 123,\n  \"subCodigoH\": 1,\n  \"nombreH\": \"LAVAMANOS ALUVIA\",\n  \"referenciaH\": \"O60691031H\",\n  \"unidadH\": \"MTR\",\n  \"referenciaP\": \"O60691031\",\n  \"unidadP\": \"94\",\n  \"factor\": 1.4\n}"
						},
						"url": {
							"raw": "http://localhost:9000/equivalencia",
							"protocol": "http",
							"host": [
								"localhost"
							],
							"port": "9000",
							"path": [
								"equivalencia"
							]
						}
					},
					"status": "Conflict",
					"code": 409,
					"_postman_previewlanguage": "json",
					"header": [
						{
							"key": "Content-Type",
							"value": "application/json"
						}
					],
					"cookie": [],
					"body": "{\n  \"success\": false,\n  \"message\": \"La equivalencia ya existe\"\n}"
				}
			]
		}
	]
}
